{"/Users/agiammarchi/git/hyperHTML-Element/test.js":{"path":"/Users/agiammarchi/git/hyperHTML-Element/test.js","s":{"1":1,"2":1,"3":1,"4":1,"5":1,"6":1,"7":1,"8":1,"9":1,"10":1,"11":1,"12":1,"13":1,"14":2,"15":1,"16":1,"17":1,"18":1,"19":1,"20":1,"21":1,"22":1,"23":2,"24":1,"25":1,"26":1,"27":1,"28":1,"29":1,"30":1,"31":1,"32":1,"33":1,"34":1,"35":1,"36":1,"37":1,"38":1,"39":1,"40":1,"41":1,"42":1,"43":1,"44":1,"45":1,"46":1,"47":7,"48":1,"49":2,"50":6,"51":1,"52":1,"53":1,"54":1,"55":1,"56":1,"57":1,"58":1,"59":1,"60":1,"61":1,"62":1,"63":1,"64":1,"65":1,"66":1,"67":1,"68":1,"69":2,"70":1,"71":1,"72":1,"73":1,"74":1,"75":2,"76":1,"77":1,"78":1,"79":1,"80":1,"81":1,"82":1,"83":1,"84":1,"85":1,"86":2,"87":1,"88":1,"89":1,"90":1,"91":1,"92":1,"93":1,"94":1,"95":1,"96":1,"97":1,"98":2,"99":1,"100":1,"101":1,"102":1,"103":1,"104":1,"105":1,"106":1,"107":1,"108":1,"109":1,"110":1,"111":2,"112":1,"113":1,"114":1,"115":1,"116":1,"117":1,"118":1,"119":1,"120":1,"121":3,"122":1,"123":1,"124":1,"125":1,"126":1,"127":1,"128":1,"129":1,"130":1,"131":1,"132":2,"133":1,"134":1,"135":1,"136":1,"137":1,"138":1,"139":1,"140":1,"141":1,"142":1,"143":1,"144":1,"145":1,"146":1,"147":1,"148":1,"149":1,"150":1,"151":1,"152":1,"153":1,"154":1,"155":1,"156":1,"157":1,"158":1,"159":1,"160":1,"161":1,"162":1,"163":1,"164":1,"165":1,"166":1,"167":1,"168":1,"169":1,"170":1,"171":1},"b":{"1":[1,1],"2":[1,1],"3":[1,1],"4":[1,1],"5":[1,1],"6":[1,1],"7":[1,1]},"f":{"1":1,"2":1,"3":2,"4":1,"5":1,"6":1,"7":1,"8":1,"9":2,"10":1,"11":1,"12":1,"13":7,"14":1,"15":2,"16":6,"17":2,"18":1,"19":1,"20":1,"21":2,"22":1,"23":2,"24":1,"25":1,"26":2,"27":1,"28":1,"29":1,"30":2,"31":1,"32":3,"33":1,"34":2,"35":1,"36":1,"37":1,"38":1,"39":1},"fnMap":{"1":{"name":"(anonymous_1)","line":19,"loc":{"start":{"line":19,"column":30},"end":{"line":19,"column":33}}},"2":{"name":"(anonymous_2)","line":23,"loc":{"start":{"line":23,"column":13},"end":{"line":23,"column":16}}},"3":{"name":"(anonymous_3)","line":25,"loc":{"start":{"line":25,"column":31},"end":{"line":25,"column":34}}},"4":{"name":"(anonymous_4)","line":29,"loc":{"start":{"line":29,"column":13},"end":{"line":29,"column":23}}},"5":{"name":"(anonymous_5)","line":35,"loc":{"start":{"line":35,"column":17},"end":{"line":35,"column":20}}},"6":{"name":"(anonymous_6)","line":40,"loc":{"start":{"line":40,"column":9},"end":{"line":40,"column":12}}},"7":{"name":"(anonymous_7)","line":44,"loc":{"start":{"line":44,"column":26},"end":{"line":44,"column":29}}},"8":{"name":"(anonymous_8)","line":48,"loc":{"start":{"line":48,"column":19},"end":{"line":48,"column":22}}},"9":{"name":"(anonymous_9)","line":52,"loc":{"start":{"line":52,"column":8},"end":{"line":52,"column":11}}},"10":{"name":"(anonymous_10)","line":69,"loc":{"start":{"line":69,"column":11},"end":{"line":69,"column":23}}},"11":{"name":"(anonymous_11)","line":71,"loc":{"start":{"line":71,"column":11},"end":{"line":71,"column":23}}},"12":{"name":"(anonymous_12)","line":92,"loc":{"start":{"line":92,"column":32},"end":{"line":92,"column":35}}},"13":{"name":"(anonymous_13)","line":96,"loc":{"start":{"line":96,"column":33},"end":{"line":96,"column":36}}},"14":{"name":"(anonymous_14)","line":100,"loc":{"start":{"line":100,"column":13},"end":{"line":100,"column":16}}},"15":{"name":"(anonymous_15)","line":104,"loc":{"start":{"line":104,"column":13},"end":{"line":104,"column":21}}},"16":{"name":"(anonymous_16)","line":108,"loc":{"start":{"line":108,"column":28},"end":{"line":108,"column":31}}},"17":{"name":"(anonymous_17)","line":140,"loc":{"start":{"line":140,"column":33},"end":{"line":140,"column":36}}},"18":{"name":"(anonymous_18)","line":143,"loc":{"start":{"line":143,"column":11},"end":{"line":143,"column":14}}},"19":{"name":"(anonymous_19)","line":146,"loc":{"start":{"line":146,"column":28},"end":{"line":146,"column":31}}},"20":{"name":"(anonymous_20)","line":154,"loc":{"start":{"line":154,"column":11},"end":{"line":154,"column":14}}},"21":{"name":"(anonymous_21)","line":155,"loc":{"start":{"line":155,"column":21},"end":{"line":155,"column":24}}},"22":{"name":"(anonymous_22)","line":167,"loc":{"start":{"line":167,"column":11},"end":{"line":167,"column":14}}},"23":{"name":"(anonymous_23)","line":176,"loc":{"start":{"line":176,"column":33},"end":{"line":176,"column":36}}},"24":{"name":"(anonymous_24)","line":179,"loc":{"start":{"line":179,"column":28},"end":{"line":179,"column":31}}},"25":{"name":"(anonymous_25)","line":191,"loc":{"start":{"line":191,"column":13},"end":{"line":191,"column":41}}},"26":{"name":"(anonymous_26)","line":206,"loc":{"start":{"line":206,"column":33},"end":{"line":206,"column":36}}},"27":{"name":"(anonymous_27)","line":209,"loc":{"start":{"line":209,"column":11},"end":{"line":209,"column":14}}},"28":{"name":"(anonymous_28)","line":222,"loc":{"start":{"line":222,"column":32},"end":{"line":222,"column":35}}},"29":{"name":"(anonymous_29)","line":225,"loc":{"start":{"line":225,"column":15},"end":{"line":225,"column":18}}},"30":{"name":"(anonymous_30)","line":239,"loc":{"start":{"line":239,"column":11},"end":{"line":239,"column":14}}},"31":{"name":"(anonymous_31)","line":240,"loc":{"start":{"line":240,"column":11},"end":{"line":240,"column":14}}},"32":{"name":"(anonymous_32)","line":257,"loc":{"start":{"line":257,"column":20},"end":{"line":257,"column":23}}},"33":{"name":"(anonymous_33)","line":258,"loc":{"start":{"line":258,"column":11},"end":{"line":258,"column":14}}},"34":{"name":"(anonymous_34)","line":276,"loc":{"start":{"line":276,"column":11},"end":{"line":276,"column":14}}},"35":{"name":"(anonymous_35)","line":288,"loc":{"start":{"line":288,"column":15},"end":{"line":288,"column":23}}},"36":{"name":"(anonymous_36)","line":305,"loc":{"start":{"line":305,"column":20},"end":{"line":305,"column":23}}},"37":{"name":"(anonymous_37)","line":308,"loc":{"start":{"line":308,"column":15},"end":{"line":308,"column":23}}},"38":{"name":"(anonymous_38)","line":337,"loc":{"start":{"line":337,"column":20},"end":{"line":337,"column":23}}},"39":{"name":"(anonymous_39)","line":338,"loc":{"start":{"line":338,"column":10},"end":{"line":338,"column":13}}}},"statementMap":{"1":{"start":{"line":1,"column":0},"end":{"line":1,"column":33}},"2":{"start":{"line":2,"column":0},"end":{"line":2,"column":60}},"3":{"start":{"line":4,"column":0},"end":{"line":4,"column":33}},"4":{"start":{"line":5,"column":0},"end":{"line":5,"column":48}},"5":{"start":{"line":6,"column":0},"end":{"line":6,"column":33}},"6":{"start":{"line":8,"column":0},"end":{"line":8,"column":33}},"7":{"start":{"line":10,"column":0},"end":{"line":10,"column":36}},"8":{"start":{"line":11,"column":0},"end":{"line":11,"column":29}},"9":{"start":{"line":12,"column":0},"end":{"line":12,"column":29}},"10":{"start":{"line":13,"column":0},"end":{"line":13,"column":23}},"11":{"start":{"line":15,"column":0},"end":{"line":15,"column":48}},"12":{"start":{"line":20,"column":4},"end":{"line":20,"column":23}},"13":{"start":{"line":23,"column":18},"end":{"line":23,"column":31}},"14":{"start":{"line":26,"column":4},"end":{"line":26,"column":19}},"15":{"start":{"line":30,"column":4},"end":{"line":30,"column":32}},"16":{"start":{"line":31,"column":4},"end":{"line":31,"column":21}},"17":{"start":{"line":32,"column":4},"end":{"line":32,"column":16}},"18":{"start":{"line":36,"column":4},"end":{"line":36,"column":43}},"19":{"start":{"line":37,"column":4},"end":{"line":37,"column":17}},"20":{"start":{"line":41,"column":4},"end":{"line":41,"column":32}},"21":{"start":{"line":45,"column":4},"end":{"line":45,"column":49}},"22":{"start":{"line":49,"column":4},"end":{"line":49,"column":42}},"23":{"start":{"line":53,"column":4},"end":{"line":53,"column":62}},"24":{"start":{"line":58,"column":0},"end":{"line":58,"column":26}},"25":{"start":{"line":61,"column":0},"end":{"line":61,"column":41}},"26":{"start":{"line":63,"column":0},"end":{"line":63,"column":92}},"27":{"start":{"line":64,"column":0},"end":{"line":64,"column":82}},"28":{"start":{"line":66,"column":0},"end":{"line":66,"column":25}},"29":{"start":{"line":67,"column":0},"end":{"line":67,"column":69}},"30":{"start":{"line":68,"column":0},"end":{"line":68,"column":44}},"31":{"start":{"line":69,"column":0},"end":{"line":69,"column":88}},"32":{"start":{"line":69,"column":25},"end":{"line":69,"column":80}},"33":{"start":{"line":71,"column":0},"end":{"line":357,"column":8}},"34":{"start":{"line":73,"column":2},"end":{"line":73,"column":56}},"35":{"start":{"line":75,"column":2},"end":{"line":75,"column":63}},"36":{"start":{"line":76,"column":2},"end":{"line":76,"column":110}},"37":{"start":{"line":77,"column":2},"end":{"line":77,"column":90}},"38":{"start":{"line":79,"column":2},"end":{"line":79,"column":19}},"39":{"start":{"line":80,"column":2},"end":{"line":80,"column":135}},"40":{"start":{"line":81,"column":2},"end":{"line":81,"column":68}},"41":{"start":{"line":82,"column":2},"end":{"line":82,"column":137}},"42":{"start":{"line":84,"column":2},"end":{"line":84,"column":35}},"43":{"start":{"line":85,"column":2},"end":{"line":85,"column":56}},"44":{"start":{"line":87,"column":2},"end":{"line":87,"column":49}},"45":{"start":{"line":88,"column":2},"end":{"line":88,"column":46}},"46":{"start":{"line":93,"column":6},"end":{"line":93,"column":25}},"47":{"start":{"line":97,"column":6},"end":{"line":97,"column":40}},"48":{"start":{"line":101,"column":6},"end":{"line":101,"column":40}},"49":{"start":{"line":105,"column":6},"end":{"line":105,"column":40}},"50":{"start":{"line":109,"column":6},"end":{"line":109,"column":25}},"51":{"start":{"line":114,"column":2},"end":{"line":114,"column":29}},"52":{"start":{"line":115,"column":2},"end":{"line":115,"column":21}},"53":{"start":{"line":116,"column":2},"end":{"line":116,"column":19}},"54":{"start":{"line":117,"column":2},"end":{"line":117,"column":19}},"55":{"start":{"line":118,"column":2},"end":{"line":118,"column":26}},"56":{"start":{"line":119,"column":2},"end":{"line":119,"column":26}},"57":{"start":{"line":120,"column":2},"end":{"line":120,"column":20}},"58":{"start":{"line":121,"column":2},"end":{"line":121,"column":95}},"59":{"start":{"line":122,"column":2},"end":{"line":122,"column":119}},"60":{"start":{"line":124,"column":2},"end":{"line":124,"column":28}},"61":{"start":{"line":125,"column":2},"end":{"line":125,"column":78}},"62":{"start":{"line":127,"column":2},"end":{"line":127,"column":21}},"63":{"start":{"line":128,"column":2},"end":{"line":128,"column":106}},"64":{"start":{"line":130,"column":2},"end":{"line":130,"column":25}},"65":{"start":{"line":131,"column":2},"end":{"line":131,"column":90}},"66":{"start":{"line":135,"column":2},"end":{"line":135,"column":37}},"67":{"start":{"line":136,"column":2},"end":{"line":136,"column":25}},"68":{"start":{"line":137,"column":2},"end":{"line":137,"column":32}},"69":{"start":{"line":141,"column":6},"end":{"line":141,"column":21}},"70":{"start":{"line":144,"column":6},"end":{"line":144,"column":57}},"71":{"start":{"line":148,"column":2},"end":{"line":148,"column":27}},"72":{"start":{"line":149,"column":2},"end":{"line":149,"column":20}},"73":{"start":{"line":150,"column":2},"end":{"line":150,"column":34}},"74":{"start":{"line":154,"column":16},"end":{"line":154,"column":33}},"75":{"start":{"line":156,"column":6},"end":{"line":156,"column":21}},"76":{"start":{"line":159,"column":2},"end":{"line":159,"column":33}},"77":{"start":{"line":160,"column":2},"end":{"line":160,"column":23}},"78":{"start":{"line":161,"column":2},"end":{"line":161,"column":32}},"79":{"start":{"line":162,"column":2},"end":{"line":162,"column":32}},"80":{"start":{"line":163,"column":2},"end":{"line":163,"column":32}},"81":{"start":{"line":164,"column":2},"end":{"line":164,"column":61}},"82":{"start":{"line":168,"column":6},"end":{"line":168,"column":56}},"83":{"start":{"line":171,"column":2},"end":{"line":171,"column":31}},"84":{"start":{"line":172,"column":2},"end":{"line":172,"column":22}},"85":{"start":{"line":173,"column":2},"end":{"line":173,"column":32}},"86":{"start":{"line":177,"column":6},"end":{"line":177,"column":21}},"87":{"start":{"line":180,"column":6},"end":{"line":180,"column":45}},"88":{"start":{"line":184,"column":2},"end":{"line":184,"column":36}},"89":{"start":{"line":186,"column":2},"end":{"line":186,"column":57}},"90":{"start":{"line":187,"column":2},"end":{"line":195,"column":4}},"91":{"start":{"line":192,"column":8},"end":{"line":192,"column":40}},"92":{"start":{"line":197,"column":2},"end":{"line":197,"column":24}},"93":{"start":{"line":198,"column":2},"end":{"line":198,"column":32}},"94":{"start":{"line":199,"column":2},"end":{"line":199,"column":19}},"95":{"start":{"line":200,"column":2},"end":{"line":200,"column":62}},"96":{"start":{"line":201,"column":2},"end":{"line":201,"column":36}},"97":{"start":{"line":202,"column":2},"end":{"line":202,"column":50}},"98":{"start":{"line":207,"column":6},"end":{"line":207,"column":21}},"99":{"start":{"line":210,"column":6},"end":{"line":210,"column":66}},"100":{"start":{"line":214,"column":2},"end":{"line":214,"column":38}},"101":{"start":{"line":216,"column":2},"end":{"line":216,"column":25}},"102":{"start":{"line":217,"column":2},"end":{"line":217,"column":32}},"103":{"start":{"line":218,"column":2},"end":{"line":218,"column":19}},"104":{"start":{"line":223,"column":6},"end":{"line":223,"column":30}},"105":{"start":{"line":225,"column":20},"end":{"line":225,"column":37}},"106":{"start":{"line":225,"column":38},"end":{"line":225,"column":50}},"107":{"start":{"line":228,"column":2},"end":{"line":228,"column":33}},"108":{"start":{"line":230,"column":2},"end":{"line":230,"column":23}},"109":{"start":{"line":231,"column":2},"end":{"line":231,"column":24}},"110":{"start":{"line":232,"column":2},"end":{"line":235,"column":4}},"111":{"start":{"line":239,"column":16},"end":{"line":239,"column":62}},"112":{"start":{"line":240,"column":16},"end":{"line":240,"column":67}},"113":{"start":{"line":243,"column":2},"end":{"line":243,"column":42}},"114":{"start":{"line":245,"column":2},"end":{"line":245,"column":27}},"115":{"start":{"line":246,"column":2},"end":{"line":246,"column":58}},"116":{"start":{"line":247,"column":2},"end":{"line":247,"column":31}},"117":{"start":{"line":248,"column":2},"end":{"line":248,"column":35}},"118":{"start":{"line":251,"column":2},"end":{"line":251,"column":41}},"119":{"start":{"line":252,"column":2},"end":{"line":252,"column":30}},"120":{"start":{"line":253,"column":2},"end":{"line":253,"column":44}},"121":{"start":{"line":257,"column":25},"end":{"line":257,"column":82}},"122":{"start":{"line":258,"column":16},"end":{"line":258,"column":96}},"123":{"start":{"line":261,"column":2},"end":{"line":261,"column":52}},"124":{"start":{"line":263,"column":2},"end":{"line":263,"column":32}},"125":{"start":{"line":264,"column":2},"end":{"line":264,"column":32}},"126":{"start":{"line":265,"column":2},"end":{"line":265,"column":31}},"127":{"start":{"line":266,"column":2},"end":{"line":266,"column":35}},"128":{"start":{"line":268,"column":2},"end":{"line":268,"column":65}},"129":{"start":{"line":269,"column":2},"end":{"line":269,"column":46}},"130":{"start":{"line":270,"column":2},"end":{"line":270,"column":50}},"131":{"start":{"line":274,"column":2},"end":{"line":274,"column":27}},"132":{"start":{"line":276,"column":16},"end":{"line":276,"column":35}},"133":{"start":{"line":278,"column":2},"end":{"line":278,"column":33}},"134":{"start":{"line":280,"column":2},"end":{"line":280,"column":43}},"135":{"start":{"line":281,"column":2},"end":{"line":281,"column":43}},"136":{"start":{"line":283,"column":2},"end":{"line":283,"column":79}},"137":{"start":{"line":286,"column":2},"end":{"line":286,"column":29}},"138":{"start":{"line":289,"column":6},"end":{"line":289,"column":27}},"139":{"start":{"line":293,"column":2},"end":{"line":293,"column":54}},"140":{"start":{"line":295,"column":2},"end":{"line":295,"column":33}},"141":{"start":{"line":296,"column":2},"end":{"line":296,"column":35}},"142":{"start":{"line":297,"column":2},"end":{"line":300,"column":4}},"143":{"start":{"line":306,"column":6},"end":{"line":306,"column":20}},"144":{"start":{"line":309,"column":6},"end":{"line":309,"column":50}},"145":{"start":{"line":313,"column":2},"end":{"line":313,"column":39}},"146":{"start":{"line":315,"column":2},"end":{"line":315,"column":26}},"147":{"start":{"line":316,"column":2},"end":{"line":316,"column":25}},"148":{"start":{"line":317,"column":2},"end":{"line":317,"column":35}},"149":{"start":{"line":318,"column":2},"end":{"line":321,"column":4}},"150":{"start":{"line":326,"column":2},"end":{"line":326,"column":56}},"151":{"start":{"line":328,"column":2},"end":{"line":328,"column":34}},"152":{"start":{"line":329,"column":2},"end":{"line":329,"column":26}},"153":{"start":{"line":330,"column":2},"end":{"line":330,"column":49}},"154":{"start":{"line":330,"column":23},"end":{"line":330,"column":46}},"155":{"start":{"line":331,"column":2},"end":{"line":334,"column":4}},"156":{"start":{"line":337,"column":25},"end":{"line":337,"column":41}},"157":{"start":{"line":341,"column":2},"end":{"line":341,"column":28}},"158":{"start":{"line":342,"column":2},"end":{"line":342,"column":19}},"159":{"start":{"line":343,"column":2},"end":{"line":343,"column":80}},"160":{"start":{"line":344,"column":2},"end":{"line":344,"column":77}},"161":{"start":{"line":345,"column":2},"end":{"line":345,"column":56}},"162":{"start":{"line":346,"column":2},"end":{"line":346,"column":20}},"163":{"start":{"line":347,"column":2},"end":{"line":347,"column":14}},"164":{"start":{"line":348,"column":2},"end":{"line":348,"column":55}},"165":{"start":{"line":349,"column":2},"end":{"line":349,"column":24}},"166":{"start":{"line":350,"column":2},"end":{"line":350,"column":65}},"167":{"start":{"line":351,"column":2},"end":{"line":351,"column":21}},"168":{"start":{"line":352,"column":2},"end":{"line":352,"column":76}},"169":{"start":{"line":354,"column":2},"end":{"line":354,"column":49}},"170":{"start":{"line":355,"column":2},"end":{"line":355,"column":21}},"171":{"start":{"line":356,"column":2},"end":{"line":356,"column":19}}},"branchMap":{"1":{"line":77,"type":"binary-expr","locations":[{"start":{"line":77,"column":16},"end":{"line":77,"column":34}},{"start":{"line":77,"column":38},"end":{"line":77,"column":71}}]},"2":{"line":121,"type":"binary-expr","locations":[{"start":{"line":121,"column":16},"end":{"line":121,"column":34}},{"start":{"line":121,"column":38},"end":{"line":121,"column":63}}]},"3":{"line":180,"type":"binary-expr","locations":[{"start":{"line":180,"column":22},"end":{"line":180,"column":34}},{"start":{"line":180,"column":38},"end":{"line":180,"column":39}}]},"4":{"line":233,"type":"binary-expr","locations":[{"start":{"line":233,"column":4},"end":{"line":233,"column":27}},{"start":{"line":233,"column":31},"end":{"line":233,"column":47}}]},"5":{"line":319,"type":"binary-expr","locations":[{"start":{"line":319,"column":4},"end":{"line":319,"column":30}},{"start":{"line":319,"column":34},"end":{"line":319,"column":50}}]},"6":{"line":350,"type":"binary-expr","locations":[{"start":{"line":350,"column":16},"end":{"line":350,"column":27}},{"start":{"line":350,"column":31},"end":{"line":350,"column":42}}]},"7":{"line":352,"type":"binary-expr","locations":[{"start":{"line":352,"column":16},"end":{"line":352,"column":33}},{"start":{"line":352,"column":37},"end":{"line":352,"column":47}}]}}},"/Users/agiammarchi/git/hyperHTML-Element/cjs/index.js":{"path":"/Users/agiammarchi/git/hyperHTML-Element/cjs/index.js","s":{"1":3,"2":3,"3":3,"4":3,"5":3,"6":3,"7":3,"8":3,"9":2,"10":3,"11":2,"12":3,"13":2,"14":3,"15":2,"16":16,"17":16,"18":16,"19":16,"20":16,"21":3,"22":2,"23":1,"24":1,"25":4,"26":4,"27":1,"28":3,"29":4,"30":3,"31":16,"32":6,"33":5,"34":1,"35":3,"36":7,"37":1,"38":6,"39":16,"40":16,"41":8,"42":8,"43":4,"44":2,"45":2,"46":1,"47":3,"48":2,"49":8,"50":8,"51":8,"52":10,"53":8,"54":8,"55":1,"56":9,"57":3,"58":8,"59":2,"60":8,"61":7,"62":16,"63":67,"64":1,"65":1,"66":1,"67":1,"68":16,"69":15,"70":4,"71":16,"72":1,"73":1,"74":1,"75":1,"76":9,"77":6,"78":1,"79":6,"80":1,"81":1,"82":1,"83":15,"84":16,"85":16,"86":4,"87":3,"88":2,"89":14,"90":6,"91":6,"92":6,"93":6,"94":6,"95":6,"96":5,"97":6,"98":3,"99":3,"100":3,"101":3,"102":3,"103":3,"104":3,"105":2,"106":1,"107":3,"108":3,"109":3,"110":2,"111":2,"112":1,"113":156,"114":3,"115":1,"116":1,"117":150,"118":80,"119":9,"120":9,"121":1,"122":9,"123":9,"124":1,"125":70,"126":1,"127":70,"128":1,"129":72,"130":1,"131":3,"132":1,"133":72,"134":72,"135":282,"136":2,"137":70,"138":70},"b":{"1":[3,3],"2":[3,3],"3":[3,3,3],"4":[3,3],"5":[16,13],"6":[2,1],"7":[1,3],"8":[4,3],"9":[3,1],"10":[4,3],"11":[16,11],"12":[5,1],"13":[1,6],"14":[8,8],"15":[2,2],"16":[1,1],"17":[2,1],"18":[3,2],"19":[8,2],"20":[1,7],"21":[3,6],"22":[2,6],"23":[7,1],"24":[1,66],"25":[1,1],"26":[15,1],"27":[4,3],"28":[4,1],"29":[1,15],"30":[16,1],"31":[4,3],"32":[3,3,3],"33":[14,4],"34":[1,5],"35":[5,1],"36":[2,1],"37":[2,1],"38":[1,2],"39":[80,70],"40":[150,72],"41":[9,71],"42":[1,8],"43":[1,8],"44":[1,69],"45":[2,280]},"f":{"1":16,"2":1,"3":4,"4":3,"5":7,"6":4,"7":10,"8":8,"9":1,"10":4,"11":4,"12":3,"13":4,"14":2,"15":14,"16":6,"17":6,"18":1,"19":3,"20":156,"21":150,"22":72,"23":3,"24":72},"fnMap":{"1":{"name":"(anonymous_1)","line":25,"loc":{"start":{"line":25,"column":15},"end":{"line":25,"column":31}}},"2":{"name":"(anonymous_2)","line":45,"loc":{"start":{"line":45,"column":13},"end":{"line":45,"column":16}}},"3":{"name":"(anonymous_3)","line":48,"loc":{"start":{"line":48,"column":13},"end":{"line":48,"column":21}}},"4":{"name":"(anonymous_4)","line":77,"loc":{"start":{"line":77,"column":13},"end":{"line":77,"column":16}}},"5":{"name":"(anonymous_5)","line":80,"loc":{"start":{"line":80,"column":13},"end":{"line":80,"column":21}}},"6":{"name":"aCC","line":118,"loc":{"start":{"line":118,"column":17},"end":{"line":118,"column":48}}},"7":{"name":"cC","line":143,"loc":{"start":{"line":143,"column":17},"end":{"line":143,"column":31}}},"8":{"name":"(anonymous_8)","line":164,"loc":{"start":{"line":164,"column":15},"end":{"line":164,"column":34}}},"9":{"name":"(anonymous_9)","line":184,"loc":{"start":{"line":184,"column":13},"end":{"line":184,"column":16}}},"10":{"name":"(anonymous_10)","line":208,"loc":{"start":{"line":208,"column":15},"end":{"line":208,"column":23}}},"11":{"name":"(anonymous_11)","line":253,"loc":{"start":{"line":253,"column":10},"end":{"line":253,"column":13}}},"12":{"name":"(anonymous_12)","line":268,"loc":{"start":{"line":268,"column":10},"end":{"line":268,"column":18}}},"13":{"name":"(anonymous_13)","line":277,"loc":{"start":{"line":277,"column":8},"end":{"line":277,"column":11}}},"14":{"name":"(anonymous_14)","line":281,"loc":{"start":{"line":281,"column":18},"end":{"line":281,"column":21}}},"15":{"name":"(anonymous_15)","line":284,"loc":{"start":{"line":284,"column":11},"end":{"line":284,"column":14}}},"16":{"name":"(anonymous_16)","line":289,"loc":{"start":{"line":289,"column":11},"end":{"line":289,"column":19}}},"17":{"name":"(anonymous_17)","line":296,"loc":{"start":{"line":296,"column":10},"end":{"line":296,"column":26}}},"18":{"name":"(anonymous_18)","line":318,"loc":{"start":{"line":318,"column":11},"end":{"line":318,"column":22}}},"19":{"name":"(anonymous_19)","line":331,"loc":{"start":{"line":331,"column":13},"end":{"line":331,"column":16}}},"20":{"name":"(anonymous_20)","line":339,"loc":{"start":{"line":339,"column":7},"end":{"line":339,"column":10}}},"21":{"name":"checkReady","line":349,"loc":{"start":{"line":349,"column":0},"end":{"line":349,"column":29}}},"22":{"name":"invoke","line":364,"loc":{"start":{"line":364,"column":0},"end":{"line":364,"column":20}}},"23":{"name":"isPrototypeOf","line":368,"loc":{"start":{"line":368,"column":0},"end":{"line":368,"column":30}}},"24":{"name":"isReady","line":372,"loc":{"start":{"line":372,"column":0},"end":{"line":372,"column":26}}}},"statementMap":{"1":{"start":{"line":4,"column":0},"end":{"line":4,"column":72}},"2":{"start":{"line":7,"column":0},"end":{"line":7,"column":62}},"3":{"start":{"line":8,"column":0},"end":{"line":8,"column":17}},"4":{"start":{"line":9,"column":0},"end":{"line":9,"column":19}},"5":{"start":{"line":10,"column":0},"end":{"line":10,"column":40}},"6":{"start":{"line":11,"column":0},"end":{"line":11,"column":60}},"7":{"start":{"line":12,"column":0},"end":{"line":12,"column":50}},"8":{"start":{"line":13,"column":0},"end":{"line":13,"column":68}},"9":{"start":{"line":13,"column":64},"end":{"line":13,"column":66}},"10":{"start":{"line":14,"column":0},"end":{"line":14,"column":62}},"11":{"start":{"line":14,"column":49},"end":{"line":14,"column":60}},"12":{"start":{"line":15,"column":0},"end":{"line":16,"column":79}},"13":{"start":{"line":16,"column":22},"end":{"line":16,"column":77}},"14":{"start":{"line":17,"column":0},"end":{"line":18,"column":55}},"15":{"start":{"line":18,"column":34},"end":{"line":18,"column":52}},"16":{"start":{"line":26,"column":4},"end":{"line":26,"column":23}},"17":{"start":{"line":27,"column":4},"end":{"line":27,"column":34}},"18":{"start":{"line":29,"column":4},"end":{"line":29,"column":56}},"19":{"start":{"line":30,"column":4},"end":{"line":30,"column":34}},"20":{"start":{"line":39,"column":4},"end":{"line":59,"column":7}},"21":{"start":{"line":40,"column":6},"end":{"line":58,"column":8}},"22":{"start":{"line":40,"column":28},"end":{"line":58,"column":8}},"23":{"start":{"line":42,"column":46},"end":{"line":42,"column":62}},"24":{"start":{"line":46,"column":12},"end":{"line":46,"column":43}},"25":{"start":{"line":49,"column":12},"end":{"line":49,"column":49}},"26":{"start":{"line":50,"column":12},"end":{"line":53,"column":45}},"27":{"start":{"line":51,"column":14},"end":{"line":51,"column":41}},"28":{"start":{"line":53,"column":14},"end":{"line":53,"column":45}},"29":{"start":{"line":54,"column":12},"end":{"line":55,"column":66}},"30":{"start":{"line":55,"column":14},"end":{"line":55,"column":66}},"31":{"start":{"line":69,"column":4},"end":{"line":88,"column":7}},"32":{"start":{"line":72,"column":6},"end":{"line":87,"column":8}},"33":{"start":{"line":72,"column":28},"end":{"line":87,"column":8}},"34":{"start":{"line":74,"column":46},"end":{"line":74,"column":62}},"35":{"start":{"line":78,"column":12},"end":{"line":78,"column":43}},"36":{"start":{"line":81,"column":12},"end":{"line":84,"column":45}},"37":{"start":{"line":82,"column":14},"end":{"line":82,"column":41}},"38":{"start":{"line":84,"column":14},"end":{"line":84,"column":45}},"39":{"start":{"line":97,"column":4},"end":{"line":97,"column":34}},"40":{"start":{"line":98,"column":4},"end":{"line":173,"column":5}},"41":{"start":{"line":100,"column":6},"end":{"line":108,"column":8}},"42":{"start":{"line":113,"column":6},"end":{"line":131,"column":8}},"43":{"start":{"line":119,"column":12},"end":{"line":123,"column":13}},"44":{"start":{"line":120,"column":14},"end":{"line":120,"column":45}},"45":{"start":{"line":121,"column":14},"end":{"line":122,"column":75}},"46":{"start":{"line":122,"column":16},"end":{"line":122,"column":75}},"47":{"start":{"line":126,"column":12},"end":{"line":128,"column":13}},"48":{"start":{"line":127,"column":14},"end":{"line":127,"column":47}},"49":{"start":{"line":136,"column":6},"end":{"line":136,"column":50}},"50":{"start":{"line":137,"column":6},"end":{"line":137,"column":39}},"51":{"start":{"line":138,"column":6},"end":{"line":154,"column":8}},"52":{"start":{"line":144,"column":12},"end":{"line":148,"column":13}},"53":{"start":{"line":145,"column":14},"end":{"line":145,"column":45}},"54":{"start":{"line":146,"column":14},"end":{"line":147,"column":56}},"55":{"start":{"line":147,"column":16},"end":{"line":147,"column":56}},"56":{"start":{"line":149,"column":12},"end":{"line":151,"column":13}},"57":{"start":{"line":150,"column":14},"end":{"line":150,"column":49}},"58":{"start":{"line":155,"column":11},"end":{"line":173,"column":5}},"59":{"start":{"line":159,"column":6},"end":{"line":172,"column":8}},"60":{"start":{"line":167,"column":12},"end":{"line":169,"column":13}},"61":{"start":{"line":168,"column":14},"end":{"line":168,"column":47}},"62":{"start":{"line":178,"column":4},"end":{"line":190,"column":7}},"63":{"start":{"line":179,"column":6},"end":{"line":189,"column":7}},"64":{"start":{"line":180,"column":8},"end":{"line":180,"column":38}},"65":{"start":{"line":181,"column":8},"end":{"line":181,"column":34}},"66":{"start":{"line":182,"column":8},"end":{"line":188,"column":11}},"67":{"start":{"line":185,"column":12},"end":{"line":186,"column":54}},"68":{"start":{"line":199,"column":4},"end":{"line":216,"column":5}},"69":{"start":{"line":203,"column":6},"end":{"line":215,"column":8}},"70":{"start":{"line":209,"column":12},"end":{"line":212,"column":21}},"71":{"start":{"line":218,"column":4},"end":{"line":244,"column":5}},"72":{"start":{"line":219,"column":6},"end":{"line":219,"column":73}},"73":{"start":{"line":220,"column":6},"end":{"line":220,"column":51}},"74":{"start":{"line":221,"column":6},"end":{"line":221,"column":42}},"75":{"start":{"line":222,"column":6},"end":{"line":231,"column":8}},"76":{"start":{"line":223,"column":23},"end":{"line":225,"column":26}},"77":{"start":{"line":226,"column":24},"end":{"line":230,"column":9}},"78":{"start":{"line":232,"column":6},"end":{"line":238,"column":8}},"79":{"start":{"line":233,"column":24},"end":{"line":237,"column":9}},"80":{"start":{"line":239,"column":6},"end":{"line":239,"column":42}},"81":{"start":{"line":240,"column":6},"end":{"line":240,"column":52}},"82":{"start":{"line":241,"column":6},"end":{"line":241,"column":50}},"83":{"start":{"line":243,"column":6},"end":{"line":243,"column":41}},"84":{"start":{"line":245,"column":4},"end":{"line":245,"column":24}},"85":{"start":{"line":246,"column":4},"end":{"line":246,"column":17}},"86":{"start":{"line":254,"column":4},"end":{"line":264,"column":7}},"87":{"start":{"line":269,"column":4},"end":{"line":269,"column":71}},"88":{"start":{"line":281,"column":23},"end":{"line":281,"column":33}},"89":{"start":{"line":285,"column":4},"end":{"line":285,"column":60}},"90":{"start":{"line":290,"column":4},"end":{"line":290,"column":72}},"91":{"start":{"line":297,"column":4},"end":{"line":297,"column":30}},"92":{"start":{"line":298,"column":4},"end":{"line":298,"column":82}},"93":{"start":{"line":299,"column":4},"end":{"line":299,"column":56}},"94":{"start":{"line":299,"column":30},"end":{"line":299,"column":56}},"95":{"start":{"line":300,"column":4},"end":{"line":300,"column":40}},"96":{"start":{"line":300,"column":26},"end":{"line":300,"column":40}},"97":{"start":{"line":301,"column":4},"end":{"line":301,"column":16}},"98":{"start":{"line":307,"column":0},"end":{"line":307,"column":39}},"99":{"start":{"line":308,"column":0},"end":{"line":308,"column":29}},"100":{"start":{"line":309,"column":0},"end":{"line":309,"column":33}},"101":{"start":{"line":310,"column":0},"end":{"line":310,"column":29}},"102":{"start":{"line":311,"column":0},"end":{"line":311,"column":31}},"103":{"start":{"line":313,"column":0},"end":{"line":322,"column":15}},"104":{"start":{"line":314,"column":2},"end":{"line":321,"column":8}},"105":{"start":{"line":314,"column":26},"end":{"line":321,"column":8}},"106":{"start":{"line":319,"column":8},"end":{"line":319,"column":69}},"107":{"start":{"line":324,"column":0},"end":{"line":324,"column":87}},"108":{"start":{"line":329,"column":0},"end":{"line":343,"column":2}},"109":{"start":{"line":332,"column":4},"end":{"line":337,"column":34}},"110":{"start":{"line":333,"column":6},"end":{"line":333,"column":57}},"111":{"start":{"line":334,"column":6},"end":{"line":334,"column":41}},"112":{"start":{"line":337,"column":6},"end":{"line":337,"column":34}},"113":{"start":{"line":340,"column":4},"end":{"line":340,"column":46}},"114":{"start":{"line":345,"column":0},"end":{"line":347,"column":1}},"115":{"start":{"line":346,"column":2},"end":{"line":346,"column":50}},"116":{"start":{"line":349,"column":0},"end":{"line":362,"column":1}},"117":{"start":{"line":350,"column":2},"end":{"line":361,"column":3}},"118":{"start":{"line":351,"column":4},"end":{"line":356,"column":5}},"119":{"start":{"line":352,"column":6},"end":{"line":352,"column":32}},"120":{"start":{"line":353,"column":6},"end":{"line":353,"column":36}},"121":{"start":{"line":353,"column":16},"end":{"line":353,"column":36}},"122":{"start":{"line":354,"column":6},"end":{"line":354,"column":67}},"123":{"start":{"line":355,"column":6},"end":{"line":355,"column":37}},"124":{"start":{"line":355,"column":16},"end":{"line":355,"column":37}},"125":{"start":{"line":358,"column":4},"end":{"line":359,"column":71}},"126":{"start":{"line":359,"column":6},"end":{"line":359,"column":71}},"127":{"start":{"line":360,"column":4},"end":{"line":360,"column":50}},"128":{"start":{"line":364,"column":0},"end":{"line":366,"column":1}},"129":{"start":{"line":365,"column":2},"end":{"line":365,"column":7}},"130":{"start":{"line":368,"column":0},"end":{"line":370,"column":1}},"131":{"start":{"line":369,"column":2},"end":{"line":369,"column":34}},"132":{"start":{"line":372,"column":0},"end":{"line":378,"column":1}},"133":{"start":{"line":373,"column":2},"end":{"line":373,"column":16}},"134":{"start":{"line":374,"column":2},"end":{"line":375,"column":29}},"135":{"start":{"line":374,"column":7},"end":{"line":374,"column":39}},"136":{"start":{"line":374,"column":27},"end":{"line":374,"column":39}},"137":{"start":{"line":376,"column":2},"end":{"line":376,"column":45}},"138":{"start":{"line":377,"column":2},"end":{"line":377,"column":15}}},"branchMap":{"1":{"line":13,"type":"binary-expr","locations":[{"start":{"line":13,"column":30},"end":{"line":13,"column":53}},{"start":{"line":13,"column":58},"end":{"line":13,"column":66}}]},"2":{"line":14,"type":"binary-expr","locations":[{"start":{"line":14,"column":23},"end":{"line":14,"column":39}},{"start":{"line":14,"column":44},"end":{"line":14,"column":60}}]},"3":{"line":15,"type":"binary-expr","locations":[{"start":{"line":15,"column":16},"end":{"line":15,"column":43}},{"start":{"line":15,"column":47},"end":{"line":15,"column":62}},{"start":{"line":16,"column":17},"end":{"line":16,"column":77}}]},"4":{"line":17,"type":"binary-expr","locations":[{"start":{"line":17,"column":23},"end":{"line":17,"column":39}},{"start":{"line":18,"column":23},"end":{"line":18,"column":53}}]},"5":{"line":39,"type":"binary-expr","locations":[{"start":{"line":39,"column":5},"end":{"line":39,"column":28}},{"start":{"line":39,"column":32},"end":{"line":39,"column":34}}]},"6":{"line":40,"type":"if","locations":[{"start":{"line":40,"column":6},"end":{"line":40,"column":6}},{"start":{"line":40,"column":6},"end":{"line":40,"column":6}}]},"7":{"line":50,"type":"if","locations":[{"start":{"line":50,"column":12},"end":{"line":50,"column":12}},{"start":{"line":50,"column":12},"end":{"line":50,"column":12}}]},"8":{"line":50,"type":"binary-expr","locations":[{"start":{"line":50,"column":16},"end":{"line":50,"column":22}},{"start":{"line":50,"column":26},"end":{"line":50,"column":43}}]},"9":{"line":54,"type":"if","locations":[{"start":{"line":54,"column":12},"end":{"line":54,"column":12}},{"start":{"line":54,"column":12},"end":{"line":54,"column":12}}]},"10":{"line":54,"type":"binary-expr","locations":[{"start":{"line":54,"column":16},"end":{"line":54,"column":25}},{"start":{"line":54,"column":29},"end":{"line":54,"column":43}}]},"11":{"line":69,"type":"binary-expr","locations":[{"start":{"line":69,"column":5},"end":{"line":69,"column":29}},{"start":{"line":69,"column":33},"end":{"line":69,"column":35}}]},"12":{"line":72,"type":"if","locations":[{"start":{"line":72,"column":6},"end":{"line":72,"column":6}},{"start":{"line":72,"column":6},"end":{"line":72,"column":6}}]},"13":{"line":81,"type":"if","locations":[{"start":{"line":81,"column":12},"end":{"line":81,"column":12}},{"start":{"line":81,"column":12},"end":{"line":81,"column":12}}]},"14":{"line":98,"type":"if","locations":[{"start":{"line":98,"column":4},"end":{"line":98,"column":4}},{"start":{"line":98,"column":4},"end":{"line":98,"column":4}}]},"15":{"line":119,"type":"if","locations":[{"start":{"line":119,"column":12},"end":{"line":119,"column":12}},{"start":{"line":119,"column":12},"end":{"line":119,"column":12}}]},"16":{"line":121,"type":"if","locations":[{"start":{"line":121,"column":14},"end":{"line":121,"column":14}},{"start":{"line":121,"column":14},"end":{"line":121,"column":14}}]},"17":{"line":126,"type":"if","locations":[{"start":{"line":126,"column":12},"end":{"line":126,"column":12}},{"start":{"line":126,"column":12},"end":{"line":126,"column":12}}]},"18":{"line":126,"type":"binary-expr","locations":[{"start":{"line":126,"column":16},"end":{"line":126,"column":25}},{"start":{"line":126,"column":29},"end":{"line":126,"column":42}}]},"19":{"line":144,"type":"if","locations":[{"start":{"line":144,"column":12},"end":{"line":144,"column":12}},{"start":{"line":144,"column":12},"end":{"line":144,"column":12}}]},"20":{"line":146,"type":"if","locations":[{"start":{"line":146,"column":14},"end":{"line":146,"column":14}},{"start":{"line":146,"column":14},"end":{"line":146,"column":14}}]},"21":{"line":149,"type":"if","locations":[{"start":{"line":149,"column":12},"end":{"line":149,"column":12}},{"start":{"line":149,"column":12},"end":{"line":149,"column":12}}]},"22":{"line":155,"type":"if","locations":[{"start":{"line":155,"column":11},"end":{"line":155,"column":11}},{"start":{"line":155,"column":11},"end":{"line":155,"column":11}}]},"23":{"line":167,"type":"if","locations":[{"start":{"line":167,"column":12},"end":{"line":167,"column":12}},{"start":{"line":167,"column":12},"end":{"line":167,"column":12}}]},"24":{"line":179,"type":"if","locations":[{"start":{"line":179,"column":6},"end":{"line":179,"column":6}},{"start":{"line":179,"column":6},"end":{"line":179,"column":6}}]},"25":{"line":185,"type":"binary-expr","locations":[{"start":{"line":185,"column":20},"end":{"line":185,"column":31}},{"start":{"line":186,"column":21},"end":{"line":186,"column":52}}]},"26":{"line":199,"type":"if","locations":[{"start":{"line":199,"column":4},"end":{"line":199,"column":4}},{"start":{"line":199,"column":4},"end":{"line":199,"column":4}}]},"27":{"line":210,"type":"binary-expr","locations":[{"start":{"line":210,"column":14},"end":{"line":210,"column":54}},{"start":{"line":211,"column":15},"end":{"line":211,"column":32}}]},"28":{"line":210,"type":"binary-expr","locations":[{"start":{"line":210,"column":15},"end":{"line":210,"column":42}},{"start":{"line":210,"column":46},"end":{"line":210,"column":48}}]},"29":{"line":218,"type":"if","locations":[{"start":{"line":218,"column":4},"end":{"line":218,"column":4}},{"start":{"line":218,"column":4},"end":{"line":218,"column":4}}]},"30":{"line":218,"type":"binary-expr","locations":[{"start":{"line":218,"column":8},"end":{"line":218,"column":15}},{"start":{"line":218,"column":19},"end":{"line":218,"column":34}}]},"31":{"line":254,"type":"binary-expr","locations":[{"start":{"line":254,"column":11},"end":{"line":254,"column":22}},{"start":{"line":254,"column":27},"end":{"line":264,"column":5}}]},"32":{"line":256,"type":"binary-expr","locations":[{"start":{"line":256,"column":6},"end":{"line":256,"column":21}},{"start":{"line":260,"column":6},"end":{"line":260,"column":22}},{"start":{"line":263,"column":6},"end":{"line":263,"column":10}}]},"33":{"line":285,"type":"binary-expr","locations":[{"start":{"line":285,"column":11},"end":{"line":285,"column":23}},{"start":{"line":285,"column":28},"end":{"line":285,"column":58}}]},"34":{"line":298,"type":"cond-expr","locations":[{"start":{"line":298,"column":49},"end":{"line":298,"column":73}},{"start":{"line":298,"column":76},"end":{"line":298,"column":81}}]},"35":{"line":300,"type":"if","locations":[{"start":{"line":300,"column":4},"end":{"line":300,"column":4}},{"start":{"line":300,"column":4},"end":{"line":300,"column":4}}]},"36":{"line":314,"type":"if","locations":[{"start":{"line":314,"column":2},"end":{"line":314,"column":2}},{"start":{"line":314,"column":2},"end":{"line":314,"column":2}}]},"37":{"line":332,"type":"if","locations":[{"start":{"line":332,"column":4},"end":{"line":332,"column":4}},{"start":{"line":332,"column":4},"end":{"line":332,"column":4}}]},"38":{"line":345,"type":"if","locations":[{"start":{"line":345,"column":0},"end":{"line":345,"column":0}},{"start":{"line":345,"column":0},"end":{"line":345,"column":0}}]},"39":{"line":350,"type":"if","locations":[{"start":{"line":350,"column":2},"end":{"line":350,"column":2}},{"start":{"line":350,"column":2},"end":{"line":350,"column":2}}]},"40":{"line":350,"type":"binary-expr","locations":[{"start":{"line":350,"column":6},"end":{"line":350,"column":17}},{"start":{"line":350,"column":21},"end":{"line":350,"column":48}}]},"41":{"line":351,"type":"if","locations":[{"start":{"line":351,"column":4},"end":{"line":351,"column":4}},{"start":{"line":351,"column":4},"end":{"line":351,"column":4}}]},"42":{"line":353,"type":"if","locations":[{"start":{"line":353,"column":6},"end":{"line":353,"column":6}},{"start":{"line":353,"column":6},"end":{"line":353,"column":6}}]},"43":{"line":355,"type":"if","locations":[{"start":{"line":355,"column":6},"end":{"line":355,"column":6}},{"start":{"line":355,"column":6},"end":{"line":355,"column":6}}]},"44":{"line":358,"type":"if","locations":[{"start":{"line":358,"column":4},"end":{"line":358,"column":4}},{"start":{"line":358,"column":4},"end":{"line":358,"column":4}}]},"45":{"line":374,"type":"if","locations":[{"start":{"line":374,"column":7},"end":{"line":374,"column":7}},{"start":{"line":374,"column":7},"end":{"line":374,"column":7}}]}}}}